[
  {
    "title": "Dpt Comercial",
    "email": "comercial@singula.pt",
    "phone": "(+351) 924 009 275",
    "address": "Rua das Boucinhas,",
    "addressLine2": "No 751, 4805-479 Airão Santa Maria,",
    "city": "Guimarães, Portugal"
  },
  {
    "title": "Singula Portugal",
    "email": "info@singula.pt",
    "phone": "(+351) 924 009 275",
    "address": "Rua das Boucinhas,",
    "addressLine2": "No 751, 4805-479 Airão Santa Maria,",
    "city": "Guimarães, Portugal"
  },
  {
    "title": "Singula Suíça",
    "email": "info@singula.pt",
    "phone": "(+351) 924 009 275",
    "address": "Rua das Boucinhas,",
    "addressLine2": "No 751, 4805-479 Airão Santa Maria,",
    "city": "Guimarães, Portugal"
  }
]
